src/__init__.py
src/auditor_ui.py
src/billing_webhook.py
src/database.py
src/apa_writer_backend/citation_engine.py
src/apa_writer_backend/main.py
src/api/main.py
src/billing/moa_usage_ledger.py
src/billing/payment_guard.py
src/billing/paywall.py
src/billing/stripe_integration.py
src/billing/stripe_meter.py
src/billing/stripe_meters_exporter.py
src/billing/stripe_product_sync.py
src/compliance/engine.py
src/compliance/policy_pack_v1.0.1.json
src/compliance/policy_pack_v1.json
src/compliance/schemas/moa_audit.schema.json
src/compliance/schemas/usage_ledger.schema.json
src/core/__init__.py
src/core/esm.py
src/core/evaluate.py
src/core/fourier.py
src/core/geometric.py
src/core/golden_dataset.py
src/core/grammar.py
src/core/magnetic_outlier_agent.py
src/core/moa_ssg_esm_spectral_guard.py
src/core/ollama_client.py
src/core/refusal_policy.py
src/core/ssg.py
src/core/ssg_codec.py
src/core/ssg_model_builder.py
src/core/ssg_runtime.py
src/esm/__init__.py
src/esm/audit.py
src/esm/baseline_store.py
src/esm/codec.py
src/esm/core.py
src/eval/__init__.py
src/eval/harness.py
src/eval/metrics.py
src/eval/tests/__init__.py
src/eval/tests/citation_validity_test.py
src/eval/tests/source_lock_test.py
src/eval/tests/variance_test.py
src/governance/__init__.py
src/governance/audit_logger.py
src/governance/mcp_interceptor.py
src/governance/moa_gate.py
src/governor/__init__.py
src/governor/telehealth_governor.py
src/moa_telehealth/__init__.py
src/moa_telehealth/integration.py
src/moa_telehealth_governor/__init__.py
src/orchestration/task_agent.py
src/physics/__init__.py
src/physics/esm_compressor.py
src/physics/prime_codecs.py
src/reg_gateway/antigravity_reg_gateway.py
src/reg_gateway/server.py
src/reporting/__init__.py
src/reporting/pdf_proof.py
src/routing/__init__.py
src/routing/moa_router.py
src/ssg/__init__.py
src/ssg/fingerprint.py
src/store/__init__.py
src/store/esm_baseline.py
src/store/task_store.py
src/tools/__init__.py
src/tools/esm_token_optimizer.py
src/tools/phi_guard.py
teletrust-1.0.0.dist-info/METADATA
teletrust-1.0.0.dist-info/WHEEL
teletrust-1.0.0.dist-info/entry_points.txt
teletrust-1.0.0.dist-info/licenses/LICENSE
teletrust-1.0.0.dist-info/RECORD
