Metadata-Version: 2.4
Name: teletrust
Version: 1.0.0
Summary: AI-powered telehealth compliance gateway with deterministic safety
Project-URL: Homepage, https://github.com/yourusername/teletrust
Project-URL: Documentation, https://teletrust.dev/docs
Project-URL: Repository, https://github.com/yourusername/teletrust
Author-email: Michael Ordon <grzywajk@gmail.com>
License: Proprietary
License-File: LICENSE
Keywords: ai-safety,compliance,hipaa,llm-governance,telehealth
Classifier: Development Status :: 4 - Beta
Classifier: Intended Audience :: Healthcare Industry
Classifier: License :: Other/Proprietary License
Classifier: Operating System :: OS Independent
Classifier: Programming Language :: Python :: 3.11
Classifier: Topic :: Scientific/Engineering :: Artificial Intelligence
Requires-Python: >=3.10
Requires-Dist: fastapi>=0.100.0
Requires-Dist: openai>=1.0.0
Requires-Dist: pydantic>=2.0.0
Requires-Dist: requests>=2.31.0
Requires-Dist: stripe>=5.0.0
Requires-Dist: uvicorn>=0.22.0
Provides-Extra: dev
Requires-Dist: pytest-cov>=4.0.0; extra == 'dev'
Requires-Dist: pytest>=7.0.0; extra == 'dev'
Requires-Dist: ruff>=0.1.0; extra == 'dev'
